{
  "main": {
    "id": "b4c05f2c5b2c9643",
    "type": "split",
    "children": [
      {
        "id": "b1e80a2fa3fbb620",
        "type": "tabs",
        "children": [
          {
            "id": "2da5000a33314d3c",
            "type": "leaf",
            "state": {
              "type": "markdown",
              "state": {
                "file": "docs/Cuban-black-beans.md",
                "mode": "source",
                "source": false
              },
              "icon": "lucide-file",
              "title": "Cuban-black-beans"
            }
          }
        ]
      }
    ],
    "direction": "vertical"
  },
  "left": {
    "id": "c36cb0b10533bc5e",
    "type": "mobile-drawer",
    "children": [
      {
        "id": "2458790043a402a3",
        "type": "leaf",
        "state": {
          "type": "file-explorer",
          "state": {
            "sortOrder": "alphabetical"
          },
          "icon": "lucide-folder-closed",
          "title": "Files"
        }
      },
      {
        "id": "3a36f61763f88c30",
        "type": "leaf",
        "state": {
          "type": "search",
          "state": {
            "query": "",
            "matchingCase": false,
            "explainSearch": false,
            "collapseAll": false,
            "extraContext": false,
            "sortOrder": "alphabetical"
          },
          "icon": "lucide-search",
          "title": "Search"
        }
      },
      {
        "id": "28fd48162c45cecb",
        "type": "leaf",
        "state": {
          "type": "tag",
          "state": {
            "sortOrder": "frequency",
            "useHierarchy": true
          },
          "icon": "lucide-tags",
          "title": "Tags"
        }
      },
      {
        "id": "1dcb81476bcb060e",
        "type": "leaf",
        "state": {
          "type": "bookmarks",
          "state": {},
          "icon": "lucide-bookmark",
          "title": "Bookmarks"
        }
      }
    ],
    "currentTab": 0
  },
  "right": {
    "id": "019cbff6bb3394b1",
    "type": "mobile-drawer",
    "children": [
      {
        "id": "118cb37a3b8ea182",
        "type": "leaf",
        "state": {
          "type": "backlink",
          "state": {
            "file": "docs/Cuban-black-beans.md",
            "collapseAll": false,
            "extraContext": false,
            "sortOrder": "alphabetical",
            "showSearch": false,
            "searchQuery": "",
            "backlinkCollapsed": false,
            "unlinkedCollapsed": true
          },
          "icon": "links-coming-in",
          "title": "Backlinks"
        }
      },
      {
        "id": "12ab67978429a28f",
        "type": "leaf",
        "state": {
          "type": "outgoing-link",
          "state": {
            "file": "docs/Cuban-black-beans.md",
            "linksCollapsed": false,
            "unlinkedCollapsed": true
          },
          "icon": "links-going-out",
          "title": "Outgoing links"
        }
      },
      {
        "id": "74af1767282a326b",
        "type": "leaf",
        "state": {
          "type": "outline",
          "state": {
            "file": "docs/Cuban-black-beans.md"
          },
          "icon": "lucide-list",
          "title": "Outline"
        }
      }
    ],
    "currentTab": 0
  },
  "left-ribbon": {
    "hiddenItems": {
      "switcher:Open quick switcher": false,
      "graph:Open graph view": false,
      "canvas:Create new canvas": false,
      "daily-notes:Open today's daily note": false,
      "templates:Insert template": false,
      "command-palette:Open command palette": false
    }
  },
  "active": "2da5000a33314d3c",
  "lastOpenFiles": [
    "docs/cold-brew.md",
    "docs/Cuban-black-beans.md"
  ]
}